[
  {
    "usuario": "wendel",
    "termo": "",
    "data": "01/04/2026, 11:44:29",
    "resposta": "Você pesquisou sobre "
  },
  {
    "usuario": "wendel",
    "termo": "messi e o melhor jogador de todos os tempos",
    "data": "01/04/2026, 11:45:01",
    "resposta": "Você pesquisou sobre messi e o melhor jogador de todos os tempos"
  },
  {
    "usuario": "wendel",
    "termo": "",
    "data": "01/04/2026, 11:45:28",
    "resposta": "Você pesquisou sobre "
  },
  {
    "usuario": "wendel",
    "termo": "",
    "data": "01/04/2026, 11:47:35",
    "resposta": "Você pesquisou sobre "
  },
  {
    "usuario": "wendeçl",
    "termo": "",
    "data": "01/04/2026, 11:51:57",
    "resposta": "Você pesquisou sobre "
  }
]